lusk/__init__.py
lusk/__main__.py
lusk/py.typed
lusk-0.0.2.dist-info/entry_points.txt
lusk-0.0.2.dist-info/LICENSE.rst
lusk-0.0.2.dist-info/WHEEL
lusk-0.0.2.dist-info/METADATA
lusk-0.0.2.dist-info/RECORD
