Metadata-Version: 2.1
Name: lusk
Version: 0.0.2
Summary: Lusk
Home-page: https://github.com/vlek/lusk
License: GPL-3.0
Author: Derek McCammond
Author-email: derekmccammond@protonmail.com
Requires-Python: >=3.7,<4.0
Classifier: Development Status :: 1 - Planning
Classifier: License :: OSI Approved :: GNU General Public License v3 (GPLv3)
Classifier: Programming Language :: Python :: 3
Classifier: Programming Language :: Python :: 3.10
Classifier: Programming Language :: Python :: 3.7
Classifier: Programming Language :: Python :: 3.8
Classifier: Programming Language :: Python :: 3.9
Requires-Dist: click (>=8.0.1,<9.0.0)
Requires-Dist: pygame (>=2.1.2,<3.0.0)
Project-URL: Changelog, https://github.com/vlek/lusk/releases
Project-URL: Documentation, https://lusk.readthedocs.io
Project-URL: Repository, https://github.com/vlek/lusk
